{
    "forecast_data": {
        "location": {
            "name": "Cottesloe",
            "country": "AU",
            "latitude": -31.99592953241122,
            "longitude": 115.7525384242436
        },
        "current_conditions": {
            "timestamp": "2025-06-27T00:44:39+00:00",
            "temperature_c": 11.73,
            "temperature_f": 53.114000000000004,
            "humidity": 74,
            "wind_speed_mph": 7.33736,
            "wind_direction": 66,
            "description": "clear sky"
        },
        "forecast": [
            {
                "startTime": "2025-06-27T03:00:00+00:00",
                "temperature": 14.25,
                "windSpeed": 6.82285,
                "windDirection": 63,
                "shortForecast": "clear sky"
            },
            {
                "startTime": "2025-06-27T06:00:00+00:00",
                "temperature": 18.12,
                "windSpeed": 4.96614,
                "windDirection": 56,
                "shortForecast": "clear sky"
            }
        ]
    },
    "weather_report": "In the tranquil embrace of Cottesloe, this morning the skies are as clear as a glassy sea, offering up a canvas of serene azure above. The sun rises unhindered, already starting to weave its golden tapestry across the beach, promising a day kissed by gentle warmth and radiant brightness. With no clouds to shroud the sun\u2019s vivacious light, the UV index will likely grow intense as the clock rolls towards noon, coaxing care upon bare skin. It's the kind of day where nature invites you to slow down and bask in its simple glory, yet demands a reverent respect for its potent rays. A balance of comfort and protection calls for light, breathable clothing\u2014perhaps a wide-brimmed hat or sunglasses for shielding delicate eyes. Given the splendor of the day, one might amble through the peaceful, sunlit streets, pausing to peruse small shops that echo with stories of summers past, or seek solace beneath the dappled shade of a tree in the park, with a book in hand. As the clock ticks past breakfast, soft waves at the shore beckon for a leisurely morning swim or a contemplative walk along the water\u2019s edge. Today, Cottesloe bears the quintessential charm of an artist\u2019s dream, a seamless poem told by the sky.",
    "color_code": "#FFD700",
    "timestamp": "2025-06-27 08:44:40"
}