{
    "forecast_data": {
        "location": {
            "name": "Perth",
            "country": "AU",
            "latitude": -31.95751085424763,
            "longitude": 115.8565269833834
        },
        "current_conditions": {
            "timestamp": "2025-03-27T06:12:06+00:00",
            "temperature_c": 37.09,
            "temperature_f": 98.76200000000001,
            "humidity": 17,
            "wind_speed_mph": 13.802290000000001,
            "wind_direction": 70,
            "description": "clear sky"
        },
        "forecast": [
            {
                "startTime": "2025-03-27T09:00:00+00:00",
                "temperature": 35.56,
                "windSpeed": 6.53204,
                "windDirection": 166,
                "shortForecast": "scattered clouds"
            },
            {
                "startTime": "2025-03-27T12:00:00+00:00",
                "temperature": 26.68,
                "windSpeed": 7.20314,
                "windDirection": 147,
                "shortForecast": "broken clouds"
            }
        ]
    },
    "weather_report": "The skies over Perth are a study in subtle transformation today. As morning slipped into afternoon, the scattered clouds thickened into a more generous tapestry of broken clouds, creating a shifting dance of sunlight and shadow upon the city. It's not the parade of brilliant sunshine that beckons with promises of open-air frolic, but rather a more introspective affair; the softened light creates a natural glow, inviting a slower pace for the reflective soul. With these clouds dimming the harshest rays, the UV index is kindly moderated. It's a day that seems to call for a comfortable stroll through the city's numerous parks, where one can savor the serenity of a slightly subdued sky. A lightweight jacket or a cosy sweater provides just the right amount of comfort against the gentle spring breeze.\n\nThis is an afternoon fashioned for those who find contentment in the gentle rustle of leaves and the stories whispered by the clouds as they lazily drift. It's an ideal time to pause by a riverside, perhaps with a book in hand or simply to watch the world move in its calm cadence. A day like this isn't one for grand adventures or daredevil escapades; instead, it invites introspection and the simple joys of being present. Allow yourself the indulgence of a quiet caf\u00e9, tracing the rhythm of rain that isn't there\u2014or might just be on the cusp of arriving\u2014 and let the atmosphere be the companion to your contemplations.",
    "color_code": "#A9B0C2",
    "timestamp": "2025-03-27 14:12:07"
}