{
    "forecast_data": {
        "location": {
            "name": "Perth",
            "country": "AU",
            "latitude": -31.9544,
            "longitude": 115.8526
        },
        "current_conditions": {
            "timestamp": "2025-02-18T09:13:19",
            "temperature_c": 24.34,
            "temperature_f": 75.812,
            "humidity": 61,
            "wind_speed_mph": 17.26964,
            "wind_direction": 110,
            "description": "broken clouds"
        },
        "forecast": [
            {
                "startTime": "2025-02-18T12:00:00",
                "temperature": 23.82,
                "windSpeed": 13.936510000000002,
                "windDirection": 112,
                "shortForecast": "broken clouds"
            },
            {
                "startTime": "2025-02-18T15:00:00",
                "temperature": 22.77,
                "windSpeed": 14.876050000000001,
                "windDirection": 115,
                "shortForecast": "overcast clouds"
            }
        ]
    },
    "weather_report": "As the afternoon gives way to the gentle embrace of evening in Perth, the skies are wrapped in a quilt of clouds. Until recently, the sun struggled with sporadic bursts through the fragmented drapes, mingling with the sky's shades of light gray. But now, as the clock ticks toward evening, a more somber canvas has unfurled an uninterrupted blanket of overcast clouds. This cloudy expanse softly veils the city in an embrace that whispers of impending introspection rather than cheer. The thought of fog weaving through the scenery is negligible, as there is no hint of its spectral presence in this temperate day. The air is cool and carries with it a mood that is pensive yet comforting, evoking a need for some warmth, both of body and spirit.\n\nUnder this vast celestial ceiling, the day seems subdued yet inviting enough for a leisurely walk along the riverside or a gentle meander through green spaces that beckon with their meditative charm. Dress in layers, perhaps a light sweater or a jacket that accommodates the cooler whispers of the air. It's a day that leans toward simple pleasures\u2014a day best spent indulging in a cup of warming chai or cradling a book as you sit by a window, the outside world a soft focus beyond the glass. In the muted glow of this cloudy evening, indoor comforts shine all the brighter, making it perfect for lounging at home, crafting comforting meals, or engaging in peaceful conversations that mirror the calm facade of the heavens above.",
    "color_code": "#788c99",
    "timestamp": "2025-02-18 17:13:19"
}