{
    "forecast_data": {
        "location": {
            "name": "Subiaco",
            "country": "AU",
            "latitude": -31.9496858886466,
            "longitude": 115.8207674458191
        },
        "current_conditions": {
            "timestamp": "2025-06-24T18:12:35+00:00",
            "temperature_c": 9.11,
            "temperature_f": 48.397999999999996,
            "humidity": 88,
            "wind_speed_mph": 0.0,
            "wind_direction": 0,
            "description": "few clouds"
        },
        "forecast": [
            {
                "startTime": "2025-06-24T21:00:00+00:00",
                "temperature": 8.43,
                "windSpeed": 8.16505,
                "windDirection": 58,
                "shortForecast": "few clouds"
            },
            {
                "startTime": "2025-06-25T00:00:00+00:00",
                "temperature": 10.37,
                "windSpeed": 6.9347,
                "windDirection": 41,
                "shortForecast": "clear sky"
            }
        ]
    },
    "weather_report": "As Tuesday unfolds in Subiaco, the early morning is blessed with the fading whispers of a few lingering clouds, revealing a canvas of a star-speckled sky now yielding to crystal clarity. With the local time advancing past two o'clock, an air of calm envelops the town, where the anticipation of a pristine day hangs gently in the atmosphere. The sun promises to rise, unwavering and resolute, carving its golden path across a dome of pure blue, casting a warm and inviting embrace upon the town. Today, the UV index quietly whispers of strength and brilliance, advising the wise to shield themselves with sunglasses and a sunhat if intending to linger under its gaze.\n\nThis is a day that beckons one to seize simple joys. A leisurely morning stroll along the quiet streets or a relaxed coffee at your favorite corner caf\u00e9 could be the perfect start, allowing the mellowness of the moment to seep into your soul. As the sun climbs, its warmth will encourage light, breathable fabrics in gentle hues\u2014perhaps a loose linen shirt paired with comfortable walking shoes to accompany you through this day of understated beauty. Gardening might be rewarded with the sun's gentle nod, or perhaps a moment of reflection on a park bench, letting thoughts drift with the passing breeze. As the world offers tranquility before the day's busier hours, cherish this serene invitation to bask in the serenity that Subiaco offers today.",
    "color_code": "#fceab7",
    "timestamp": "2025-06-25 02:12:35"
}