{
    "forecast_data": {
        "location": {
            "name": "Osborne Park",
            "country": "AU",
            "latitude": -31.90801908123256,
            "longitude": 115.8018732221881
        },
        "current_conditions": {
            "timestamp": "2025-03-26T00:39:21+00:00",
            "temperature_c": 27.64,
            "temperature_f": 81.752,
            "humidity": 42,
            "wind_speed_mph": 1.99093,
            "wind_direction": 77,
            "description": "clear sky"
        },
        "forecast": [
            {
                "startTime": "2025-03-26T03:00:00+00:00",
                "temperature": 36.61,
                "windSpeed": 9.373030000000002,
                "windDirection": 60,
                "shortForecast": "clear sky"
            },
            {
                "startTime": "2025-03-26T06:00:00+00:00",
                "temperature": 39.13,
                "windSpeed": 5.055619999999999,
                "windDirection": 118,
                "shortForecast": "clear sky"
            }
        ]
    },
    "weather_report": "As the morning unfurls in Osborne Park, an expanse of clear skies sets the stage for a tranquil day. The sun, newly risen, promises to bathe the world in its gentle, golden embrace, though the hours have yet to summon the heat of the afternoon. This is a day that meets you like a gentle friend, warm yet unobtrusive, offering the soothing clarity only a serene sky can provide. The air is crisp and clean, ushering in a sense of optimism with each breath. While the UV index is not pressing in these early hours, it will undoubtedly rise as the day matures, suggesting the subtle vigilance of sunscreen for those planning to linger outdoors. Such a day calls for light, breathable fabrics\u2014perhaps a soft cotton shirt or an airy sundress\u2014under which to celebrate the simplicity of spring.\n\nThe clarity of the atmosphere reflects the potential for uncomplicated joy, inviting you to engage in the small pleasures often overlooked. A leisurely walk through the park, the gentle rustle of leaves overhead, or a moment spent on a sun-dappled bench with a good book seem the perfect response to this day's poetic summons. There's no rush; today's allure lies in its invitation to embrace life's slower rhythms, to appreciate a moment under the sky as vast as one's imagination. This day, with its promise of good things to come, feels like a chapter ready to be written, each moment an unhurried step on the unfolding path.",
    "color_code": "#87CEEB",
    "timestamp": "2025-03-26 08:39:22"
}