{
    "forecast_data": {
        "location": {
            "name": "City Beach",
            "country": "AU",
            "latitude": -31.91659638115502,
            "longitude": 115.7577590151934
        },
        "current_conditions": {
            "timestamp": "2025-03-30T00:43:31+00:00",
            "temperature_c": 23.79,
            "temperature_f": 74.822,
            "humidity": 57,
            "wind_speed_mph": 25.322840000000003,
            "wind_direction": 70,
            "description": "clear sky"
        },
        "forecast": [
            {
                "startTime": "2025-03-30T03:00:00+00:00",
                "temperature": 23.98,
                "windSpeed": 22.280520000000003,
                "windDirection": 74,
                "shortForecast": "light rain"
            },
            {
                "startTime": "2025-03-30T06:00:00+00:00",
                "temperature": 26.18,
                "windSpeed": 21.206760000000003,
                "windDirection": 61,
                "shortForecast": "light rain"
            }
        ]
    },
    "weather_report": "As the morning unfurls over City Beach, the whispers of last night's light rain still linger in the air. Patches of silver clouds drift lazily across the canvas of dawn, carrying with them the scent of damp earth and the subtle promise of more gentle showers. The day rolls out quietly, painting the sky with muted tones that hint at the sun's presence behind its gauzy veil. The clarity of the day teeters on the edge of mystery, with the shy sun playing a game of hide and seek, offering moments of warmth that may coax an unexpected ray onto a wandering wayfarer's face. The UV index remains modest, allowing the gentle luminescence to caress the skin without urgency or caution. \n\nIt's a day perfectly tailored for leisurely strolls, with a cozy sweater draped over one's shoulders and comfortable shoes making each step a pleasure. The soundtrack of the rain's soft patter sets the rhythm for the day\u2019s activities. Perhaps, wander through the lanes of a local farmer's market, the fresh produce glistening with raindrops, or lose oneself in the tranquility of a small coffee house, the aroma of freshly ground beans enveloping the senses as the world carries on outside. Today invites quiet reflection and gentle pace, a respite from the week's hurried cadence, offering time to embrace the gentle sweep of nature's brushstrokes across the sky.",
    "color_code": "#A9A9A9",
    "timestamp": "2025-03-30 08:43:32"
}