{
    "forecast_data": {
        "location": {
            "name": "Subiaco",
            "country": "AU",
            "latitude": -31.94969125224071,
            "longitude": 115.8206840111494
        },
        "current_conditions": {
            "timestamp": "2025-04-27T12:13:32+00:00",
            "temperature_c": 16.96,
            "temperature_f": 62.528000000000006,
            "humidity": 77,
            "wind_speed_mph": 6.91233,
            "wind_direction": 190,
            "description": "clear sky"
        },
        "forecast": [
            {
                "startTime": "2025-04-27T15:00:00+00:00",
                "temperature": 16.36,
                "windSpeed": 7.247880000000001,
                "windDirection": 124,
                "shortForecast": "clear sky"
            },
            {
                "startTime": "2025-04-27T18:00:00+00:00",
                "temperature": 14.27,
                "windSpeed": 7.672910000000001,
                "windDirection": 122,
                "shortForecast": "clear sky"
            }
        ]
    },
    "weather_report": "As the sun begins to dip beneath the horizon, Subiaco finds itself enveloped in a soothing landscape of crystal-clear clarity, akin to a perfect, untouched canvas. The sky above is free from the intrusion of clouds, offering a serene azure backdrop that wanes into a soft, dusky blue as day yields to night. Today has been a quintessentially sun-drenched day, with a steady parade of sunbeams painting everything with luminous warmth. Though the forecast provided no explicit detail on the UV index, one might wisely infer that, considering the pristine sky, the sun reigned with vigor through the day, urging those to bask in its gentle glow with caution and perhaps an elegant straw hat. As evening sets in, the air cools to an inviting embrace, lending itself to a leisurely stroll along the quiet streets or a peaceful sit in a secluded caf\u00e9, perhaps with a book in hand and a sip of something comforting. Dressing for such a refined scene requires simple sophistication; a light jacket for the impending night chill and comfortable footwear to carry you through an evening of idle wanderings. This moment, caught between sun and stars, invites introspection or quiet conversation, neither rushed nor burdened with the weight of ornate activities, simply a time to revel in the gentle, unassuming beauty of a day well-lived.",
    "color_code": "#1E3A5F",
    "timestamp": "2025-04-27 20:13:33"
}