{
    "forecast_data": {
        "location": {
            "name": "Subiaco",
            "country": "AU",
            "latitude": -31.94972916359204,
            "longitude": 115.8207663272025
        },
        "current_conditions": {
            "timestamp": "2026-05-07T15:26:28+00:00",
            "temperature_c": 17.13,
            "temperature_f": 62.833999999999996,
            "humidity": 53,
            "wind_speed_mph": 12.661420000000001,
            "wind_direction": 80,
            "description": "clear sky"
        },
        "forecast": [
            {
                "startTime": "2026-05-07T18:00:00+00:00",
                "temperature": 16.52,
                "windSpeed": 15.03264,
                "windDirection": 72,
                "shortForecast": "clear sky"
            },
            {
                "startTime": "2026-05-07T21:00:00+00:00",
                "temperature": 14.56,
                "windSpeed": 14.965530000000001,
                "windDirection": 71,
                "shortForecast": "clear sky"
            }
        ]
    },
    "weather_report": "Subiaco settles under a clear, ink-blue sky tonight; stars are crisp, the air a touch cool, and the streets feel tidied by quiet. It is not a night of sun but of clean visibility and easy breathing, the sort of clarity that makes distant bells sound closer. UV is essentially asleep now, and with these cloudless hours, dawn is likely to arrive bright and unfiltered, the kind of sunshine that sharpens edges and warms stone quickly.\n\nExpect a pleasant, dry-feeling start if the clear spell lingers. A light jacket or soft sweater suits the late night and the first hours after sunrise; trade it for sleeves you can roll when the day wakes up. If you\u2019re out late, a gentle stroll or a slow lap around the piazza fits the mood; if you\u2019re up early, a coffee on a quiet terrace or a quick errand before the town stirs will feel just right. Plan on sunglasses and a touch of sunscreen later in the morning, when the sun begins to show its intent under an open sky.",
    "color_code": "#0A2342",
    "timestamp": "2026-05-07 23:26:29",
    "location": {
        "name": "Subiaco",
        "latitude": -31.94972916359204,
        "longitude": 115.8207663272025,
        "timezone": "Australia/Perth"
    }
}