{
    "forecast_data": {
        "location": {
            "name": "Subiaco",
            "country": "AU",
            "latitude": -31.94970929183988,
            "longitude": 115.8209041066613
        },
        "current_conditions": {
            "timestamp": "2026-04-22T14:44:51+00:00",
            "temperature_c": 14.77,
            "temperature_f": 58.586,
            "humidity": 72,
            "wind_speed_mph": 9.50725,
            "wind_direction": 279,
            "description": "overcast clouds"
        },
        "forecast": [
            {
                "startTime": "2026-04-22T15:00:00+00:00",
                "temperature": 14.77,
                "windSpeed": 9.50725,
                "windDirection": 279,
                "shortForecast": "overcast clouds"
            },
            {
                "startTime": "2026-04-22T18:00:00+00:00",
                "temperature": 15.1,
                "windSpeed": 17.80652,
                "windDirection": 306,
                "shortForecast": "overcast clouds"
            }
        ]
    },
    "weather_report": "Subiaco settles under a low, unbroken ceiling of cloud. At this late hour the sky is ash-gray, the stars smudged out and the moon, if it\u2019s there, kept quiet. Sunshine won\u2019t figure again tonight, and the UV index is essentially nil. The air feels even and unhurried; clarity is softened rather than sharp, with streetlights throwing small halos that fade at the edges.\n\nCloud is set to linger through midnight and the early hours, keeping the mood muted and making dawn likely to arrive in a gentle, grey key if the blanket holds. It\u2019s a night for long sleeves and a light jacket if you slip outside, comfortable shoes for a slow loop around the block, then home to a warm drink and a quiet page or two while you set out tomorrow\u2019s bag. If you\u2019re up early, expect low glare and subdued light; dress in easy layers you can peel back if the day decides to brighten.",
    "color_code": "#2F3A44",
    "timestamp": "2026-04-22 22:44:51",
    "location": {
        "name": "Subiaco",
        "latitude": -31.94970929183988,
        "longitude": 115.8209041066613,
        "timezone": "Australia/Perth"
    }
}