{
    "forecast_data": {
        "location": {
            "name": "Subiaco",
            "country": "AU",
            "latitude": -31.94969583154379,
            "longitude": 115.8208550783105
        },
        "current_conditions": {
            "timestamp": "2025-06-10T18:12:21+00:00",
            "temperature_c": 11.3,
            "temperature_f": 52.34,
            "humidity": 83,
            "wind_speed_mph": 8.0532,
            "wind_direction": 70,
            "description": "clear sky"
        },
        "forecast": [
            {
                "startTime": "2025-06-10T21:00:00+00:00",
                "temperature": 11.08,
                "windSpeed": 5.70435,
                "windDirection": 150,
                "shortForecast": "scattered clouds"
            },
            {
                "startTime": "2025-06-11T00:00:00+00:00",
                "temperature": 12.05,
                "windSpeed": 4.11608,
                "windDirection": 101,
                "shortForecast": "broken clouds"
            }
        ]
    },
    "weather_report": "As dawn gently graces Subiaco, the sky is a canvas of scattered clouds, remnants of a night that whispered promises of a new day. The forecast hints at a modest transition to broken clouds, a gentle evolution suggesting a day not quite shrouded in gloom, nor brazenly sunlit. The clarity of the day seems somewhat moderated, a soft haze of mystery clinging to the air, weaving a tapestry of subdued light and shadow. The sun, though not in full command, arches steadfastly towards its morning zenith, offering a tender embrace to those who seek it out. The UV index, a silent architect of the atmosphere, suggests moderation; a touch of sun protection would be wise for those who travel under this canopy.\n\nIn this dreamy crown of morning, spontaneity finds its charm in the gentle clime, inviting one to adorn soft layers\u2014perhaps a lightweight sweater to make peace with the ambiguous temperament of the weather. As the world stirs, activities align with tranquility: a contemplative ambulation through the neighborhood park, a turn through pages of a beloved novel while nestled in a patio nook, sipping something warm and soothing. With the complexity of natural moods around, it's a perfect day to feel the quiet thrumming of existence, wrapped in its soft gray tones, guiding us tenderly through the fabric of today into whatever tomorrow's light might bring.",
    "color_code": "#A9A9A9",
    "timestamp": "2025-06-11 02:12:22"
}