{
    "forecast_data": {
        "location": {
            "name": "West Perth",
            "country": "AU",
            "latitude": -31.95430873347433,
            "longitude": 115.8472759046343
        },
        "current_conditions": {
            "timestamp": "2026-05-22T02:55:22+00:00",
            "temperature_c": 17.31,
            "temperature_f": 63.158,
            "humidity": 57,
            "wind_speed_mph": 11.49818,
            "wind_direction": 150,
            "description": "few clouds"
        },
        "forecast": [
            {
                "startTime": "2026-05-22T03:00:00+00:00",
                "temperature": 17.12,
                "windSpeed": 10.82708,
                "windDirection": 180,
                "shortForecast": "few clouds"
            },
            {
                "startTime": "2026-05-22T06:00:00+00:00",
                "temperature": 17.95,
                "windSpeed": 12.3035,
                "windDirection": 207,
                "shortForecast": "few clouds"
            }
        ]
    },
    "weather_report": "Late morning in West Perth arrives under a clean blue dome with a few small clouds drifting lazily by. The light is honest and bright, giving the day a crisp, well-defined edge; visibility looks excellent and the sky should stay mostly open through early afternoon. As the sun climbs, expect it to feel sunnier than the season suggests, with UV likely moving from moderate toward the higher side around midday\u2014enough to warrant sunscreen, a hat, and sunglasses if you\u2019ll be out for a while.\n\nDress in light layers: a breathable shirt with something you can shrug on if shade or a breeze cools you. It\u2019s a pleasant day for unhurried errands on foot, an early lunch outdoors, watering the balcony plants, or letting a load of washing dry in the clear air. If you\u2019ve time, take a slow loop through quiet streets or sit by a window with a book; the day rewards simple, sunlit minutes before the afternoon settles.",
    "color_code": "#87CEEB",
    "timestamp": "2026-05-22 10:55:25",
    "location": {
        "name": "West Perth",
        "latitude": -31.95430873347433,
        "longitude": 115.8472759046343,
        "timezone": "Australia/Perth"
    }
}